[{"id":1,"name":"45","email":"5456","date":"27-04-2020","comment":"","product_id":2},{"id":2,"name":"s","email":"s","date":"27-04-2020","comment":"","product_id":6},{"id":3,"name":"","email":"","date":"27-04-2020","comment":"x","product_id":6},{"id":4,"name":"","email":"","date":"27-04-2020","comment":"x","product_id":6},{"id":5,"name":"Ivan","email":"ivanpolyvoda@gmail.com","date":"27-04-2020","comment":"","product_id":6},{"id":6,"name":"Ivan","email":"ivanpolyvoda@gmail.com","date":"27-04-2020","comment":"","product_id":6},{"id":7,"name":"Ivan","email":"ivanpolyvoda@gmail.com","date":"27-04-2020","comment":"","product_id":6},{"id":8,"name":"Ivan","email":"ivanpolyvoda@gmail.com","date":"07-05-2020","comment":"\u0426\u0435 \u043a\u043e\u043c\u0435\u043d\u0442\u0430\u0440","product_id":2},{"id":9,"name":"Ivan","email":"ivanpolyvoda@gmail.com","date":"07-05-2020","comment":"\u0426\u0435 \u043a\u043e\u043c\u0435\u043d\u0442\u0430\u0440","product_id":2},{"id":10,"name":"Ivan","email":"ivanpolyvoda@gmail.com","date":"07-05-2020","comment":"dsfsd","product_id":2}]